flask_python_ldap/__init__.py
flask_python_ldap-0.1.3.dist-info/METADATA
flask_python_ldap-0.1.3.dist-info/RECORD
flask_python_ldap-0.1.3.dist-info/WHEEL
flask_python_ldap-0.1.3.dist-info/top_level.txt
